fluxdb/__init__.py
fluxdb/client.py
fluxdb_driver-1.0.2.post1.dist-info/METADATA
fluxdb_driver-1.0.2.post1.dist-info/WHEEL
fluxdb_driver-1.0.2.post1.dist-info/top_level.txt
fluxdb_driver-1.0.2.post1.dist-info/RECORD
