Metadata-Version: 2.4
Name: fluxdb-driver
Version: 1.0.2.post1
Summary: Official Python driver for the FluxDB C++ Database
Home-page: https://github.com/PranavKndpl/FluxDB
Author: Pranav Kandpal
Classifier: Programming Language :: Python :: 3
Classifier: License :: OSI Approved :: MIT License
Classifier: Operating System :: OS Independent
Requires-Python: >=3.7
Dynamic: author
Dynamic: classifier
Dynamic: description
Dynamic: description-content-type
Dynamic: home-page
Dynamic: requires-python
Dynamic: summary
